moidata/__init__.py
moidata/moidata.py
moidata-0.0.1.dist-info/LICENSE
moidata-0.0.1.dist-info/METADATA
moidata-0.0.1.dist-info/WHEEL
moidata-0.0.1.dist-info/top_level.txt
moidata-0.0.1.dist-info/RECORD
