Metadata-Version: 2.1
Name: moidata
Version: 0.0.1
Summary: TRILE DATA ENTRY BY MOI
Home-page: https://github.com/moieis/Moidata.git
Author: Mohammed Eissa Alshari
Author-email: author@example.com
License: UNKNOWN
Project-URL: Bug Tracker, https://github.com/pypa/sampleproject/issues
Platform: UNKNOWN
Classifier: Programming Language :: Python :: 3
Classifier: License :: OSI Approved :: MIT License
Classifier: Operating System :: OS Independent
Requires-Python: >=3.6
License-File: LICENSE
